README.md
setup.py
espeak/__init__.py
espeak/espeakmodulecore.cpp
python_espeak.egg-info/PKG-INFO
python_espeak.egg-info/SOURCES.txt
python_espeak.egg-info/dependency_links.txt
python_espeak.egg-info/top_level.txt