Metadata-Version: 2.1
Name: python-espeak
Version: 0.6.2
Summary: Python C extension for the eSpeak speech synthesizer
Home-page: https://github.com/asrp/python-espeak
Author: Siegfried-A. Gevatter Pujals, asrp
Author-email: asrp@email.com
License: GNU GPL
Platform: posix
